ssher/__init__.py
ssher/__main__.py
ssher/batch_import.py
ssher/clipboard.py
ssher/completion.py
ssher/config.py
ssher/connection.py
ssher/crypto.py
ssher/formatting.py
ssher/models.py
ssher/password_auth.py
ssher/password_gen.py
ssher/profiles.py
ssher/recording.py
ssher/servers.py
ssher/ssh_config_export.py
ssher/sshpass_compat.py
ssher/transfer.py
ssher/vault.py
ssher/cli/__init__.py
ssher/cli/commands.py
ssher/cli/parser.py
ssher/cli/wrap.py
ssher/ui/__init__.py
ssher/ui/base.py
ssher/ui/display.py
ssher/ui/help_ui.py
ssher/ui/main_loop.py
ssher/ui/multi_exec_ui.py
ssher/ui/prompts.py
ssher/ui/status_ui.py
ssher/ui/transfer_ui.py
ssher_cli-3.0.0.dist-info/licenses/LICENSE
ssher_cli-3.0.0.dist-info/METADATA
ssher_cli-3.0.0.dist-info/WHEEL
ssher_cli-3.0.0.dist-info/entry_points.txt
ssher_cli-3.0.0.dist-info/top_level.txt
ssher_cli-3.0.0.dist-info/RECORD
