Metadata-Version: 2.4
Name: ssher-cli
Version: 3.0.0
Summary: Ultimate SSH Configuration Manager - A powerful CLI tool for managing SSH server configurations
Author: Inioluwa Adeyinka
License: MIT
Project-URL: Homepage, https://github.com/Johnniewhite/ssher
Project-URL: Documentation, https://github.com/Johnniewhite/ssher#readme
Project-URL: Repository, https://github.com/Johnniewhite/ssher
Project-URL: Issues, https://github.com/Johnniewhite/ssher/issues
Keywords: ssh,configuration,manager,sshpass,terminal,cli,devops,sysadmin
Classifier: Development Status :: 5 - Production/Stable
Classifier: Environment :: Console
Classifier: Intended Audience :: Developers
Classifier: Intended Audience :: System Administrators
Classifier: License :: OSI Approved :: MIT License
Classifier: Operating System :: OS Independent
Classifier: Operating System :: POSIX :: Linux
Classifier: Operating System :: MacOS
Classifier: Programming Language :: Python :: 3
Classifier: Programming Language :: Python :: 3.7
Classifier: Programming Language :: Python :: 3.8
Classifier: Programming Language :: Python :: 3.9
Classifier: Programming Language :: Python :: 3.10
Classifier: Programming Language :: Python :: 3.11
Classifier: Programming Language :: Python :: 3.12
Classifier: Programming Language :: Python :: 3.13
Classifier: Topic :: System :: Systems Administration
Classifier: Topic :: System :: Networking
Classifier: Topic :: Utilities
Requires-Python: >=3.7
License-File: LICENSE
Requires-Dist: cryptography>=41.0.0
Requires-Dist: pexpect>=4.8.0
Dynamic: license-file
Dynamic: requires-python
